Metadata-Version: 2.1
Name: musixmatch-py
Version: 0.2
Summary: Pythonic wrapper for the undocumented musixmatch API.
Home-page: https://github.com/sarzz2/musixmatch-py
Author: sarzz2
License: MIT
Project-URL: Documentation, https://musixmatch-py.readthedocs.io/en/latest/
Platform: UNKNOWN
Classifier: License :: OSI Approved :: MIT License
Classifier: Programming Language :: Python
Classifier: Programming Language :: Python :: 3.6
Classifier: Programming Language :: Python :: 3.7
Classifier: Programming Language :: Python :: 3.8
Classifier: Programming Language :: Python :: 3.9
Requires-Python: >=3.6
